hnlp/__init__.py
hnlp/dataprocessor/__init__.py
hnlp/dataprocessor/corpus.py
hnlp/dataprocessor/dataloader.py
hnlp/dataprocessor/preprocessor.py
hnlp/dataprocessor/sampler.py
hnlp/dataprocessor/tokenizer.py
hnlp/model/__init__.py
hnlp/model/trainer.py
hnlp/model/transformer.py
hnlp/pretrained/__init__.py
hnlp/pretrained/model.py
hnlp/pretrained/postprocessor.py
hnlp/task/__init__.py
hnlp/task/sequence_tagger/__init__.py
hnlp/task/sequence_tagger/model.py
tests/__init__.py
hnlp-0.1.dist-info/LICENSE
hnlp-0.1.dist-info/METADATA
hnlp-0.1.dist-info/WHEEL
hnlp-0.1.dist-info/top_level.txt
hnlp-0.1.dist-info/RECORD
